{"blocks":[{"id":"D3F5F6EE-2C11-4BEF-B48A-6EBBF18118D7","type":"StartBlock","disabled":false,"name":"Start","displayName":"Start","comment":"","childId":"EA14AEA1-4009-48DE-9120-94C41060556D","inputs":[{"id":"run_mode","value":"manual","type":"select","structure":{}}],"settings":[],"collapsed":[{"name":"loop","isCollapsed":false}],"x":-2239,"y":290},{"id":"F23BD9D1-DB61-4CC5-96EB-1CB8A2A90AA4","type":"EndpointBlock","disabled":false,"name":"createTerm","displayName":"Qlik Cloud Services - Create Term","comment":"Add a term to the glossary containing the source tenant name and URL ","childId":"34FFA1E0-E4BA-4204-8DA7-3D5A22E9E040","inputs":[{"id":"8253b200-5630-11ee-b2fd-350e5f792573","value":"{ $.createGlossary.id }","type":"string","structure":[]},{"id":"c58d35e0-5630-11ee-a6e7-db6b6498f098","value":"ISV Source Tenant","type":"string","structure":[]},{"id":"dda04000-5630-11ee-befb-8fbf9676df42","value":null,"type":"string","structure":[]},{"id":"f0683590-5630-11ee-bc41-87f09bdb7cb1","value":"{ $.getCurrentTenantInfo.hostnames[0] }","type":"string","structure":[]},{"id":"fc259e70-5630-11ee-a52f-1fa41edbebb5","value":"ISV","type":"string","structure":[]},{"id":"0dc39800-5631-11ee-be4f-83abc7829d44","value":null,"type":"string","structure":[]},{"id":"2030ec50-5631-11ee-9c17-45161d913a0d","value":null,"type":"string","structure":[]},{"id":"30788ec0-5631-11ee-a358-ffcea70b8008","value":null,"type":"string","structure":[]},{"id":"3fe038d0-5631-11ee-9cc0-4d24c1965989","value":null,"type":"string","structure":[]},{"id":"4980a610-5631-11ee-8f70-9764de6e36dd","value":null,"type":"string","structure":[]}],"settings":[{"id":"blendr_on_error","value":"stop","type":"select","structure":[]},{"id":"automations_censor_data","value":false,"type":"checkbox","structure":[]}],"collapsed":[{"name":"loop","isCollapsed":false}],"x":-2569,"y":762,"datasourcetype_guid":"61a87510-c7a3-11ea-95da-0fb0c241e75c","endpoint_guid":"82432160-5630-11ee-b2f4-3b97c6c1c76e","endpoint_role":"create"},{"id":"647EB098-9B83-4528-8FE2-75D991182EE5","type":"EndpointBlock","disabled":false,"name":"createGlossary","displayName":"Qlik Cloud Services - Create Glossary","comment":"Create a new glossary on the source tenant to persist all multitenant deployment-related metadata","childId":"9A281DDB-1038-44A7-8DAC-6762A950DD56","inputs":[{"id":"b772d1e0-5609-11ee-9194-27d723b3c3a8","value":"{ $.businessGlossaryName }","type":"string","structure":[]},{"id":"b7810170-5609-11ee-90e4-d3646ac7e81c","value":"The glossary provides a centralized, structured repository of deployment-related metadata and standardized terminology to support ISV solution delivery. It includes key customer information such as organization names, Qlik Cloud tenant URLs, and associated applications to be deployed.","type":"string","structure":[]},{"id":"b790c2b0-5609-11ee-82da-95f092925895","value":"{ $.filterList[0].id }","type":"string","structure":[]}],"settings":[{"id":"blendr_on_error","value":"stop","type":"select","structure":[]},{"id":"automations_censor_data","value":false,"type":"checkbox","structure":[]}],"collapsed":[{"name":"loop","isCollapsed":false}],"x":-2619,"y":668,"datasourcetype_guid":"61a87510-c7a3-11ea-95da-0fb0c241e75c","endpoint_guid":"b752cb40-5609-11ee-9bb1-014aa10c2b62","endpoint_role":"create"},{"id":"FB0667A9-B389-4ADB-9615-9555F36AA0E1","type":"EndpointBlock","disabled":false,"name":"listSpaces","displayName":"Qlik Cloud Services - List Spaces","comment":"Get spaces on the source tenant","childId":"BA2CA198-C33B-4F9B-A2A8-3E81A96A95F2","inputs":[],"settings":[{"id":"maxitemcount","value":"","type":"string","structure":[]},{"id":"blendr_on_error","value":"stop","type":"select","structure":[]},{"id":"cache","value":"0","type":"select","structure":[]},{"id":"automations_censor_data","value":false,"type":"checkbox","structure":[]}],"collapsed":[{"name":"loop","isCollapsed":true}],"x":-2239,"y":530,"loopBlockId":null,"datasourcetype_guid":"61a87510-c7a3-11ea-95da-0fb0c241e75c","endpoint_guid":"42815920-5f18-11eb-8321-91b1587b6c06","endpoint_role":"list"},{"id":"BA2CA198-C33B-4F9B-A2A8-3E81A96A95F2","type":"FilterListBlock","disabled":false,"name":"filterList","displayName":"Filter over Qlik Cloud Services - List Spaces - Filter List","comment":"Obtain shared space named \"Staging\"","childId":"647EB098-9B83-4528-8FE2-75D991182EE5","inputs":[{"id":"list","value":"{ $.listSpaces }","type":"string","structure":[]},{"id":"conditions","value":{"mode":"all","conditions":[{"input1":"name","input2":"{ $.sharedSpaceName }","operator":"="}]},"type":"custom","structure":[]}],"settings":[{"id":"automations_censor_data","value":false,"type":"checkbox","structure":[]}],"collapsed":[{"name":"loop","isCollapsed":true}],"x":-3027,"y":369,"loopBlockId":null},{"id":"EA14AEA1-4009-48DE-9120-94C41060556D","type":"VariableBlock","disabled":false,"name":"sharedSpaceName","displayName":"Variable - sharedSpaceName","comment":"Name of the shared space on the source tenant","childId":"905AFE8C-0F54-49E0-837B-7132916D215C","inputs":[],"settings":[],"collapsed":[{"name":"loop","isCollapsed":false}],"x":-2500,"y":602,"variableGuid":"4341C652-65B7-4B0A-B5B6-F1BDAB3579DB","operations":[{"id":"set_value","key":"DB079338-34BF-449C-B875-253F9FC744AB","name":"Set value of { variable }","value":"Staging"}]},{"id":"9A281DDB-1038-44A7-8DAC-6762A950DD56","type":"EndpointBlock","disabled":false,"name":"getCurrentTenantInfo","displayName":"Qlik Cloud Services - Get Current Tenant Info","comment":"Obtain source tenant URL","childId":"F23BD9D1-DB61-4CC5-96EB-1CB8A2A90AA4","inputs":[],"settings":[{"id":"blendr_on_error","value":"stop","type":"select","structure":[]},{"id":"cache","value":"0","type":"select","structure":[]},{"id":"automations_censor_data","value":false,"type":"checkbox","structure":[]}],"collapsed":[{"name":"loop","isCollapsed":false}],"x":-2025,"y":569,"datasourcetype_guid":"61a87510-c7a3-11ea-95da-0fb0c241e75c","endpoint_guid":"55051480-cb86-11ec-b746-892c1d04114e","endpoint_role":"get"},{"id":"34FFA1E0-E4BA-4204-8DA7-3D5A22E9E040","type":"ShowBlock","disabled":false,"name":"output","displayName":"Output","comment":"Show the previously created term in the glossary","childId":null,"inputs":[{"id":"input","value":"{ $.createTerm }","type":"string","structure":[]}],"settings":[{"id":"display_mode","value":"add","type":"select","structure":[]}],"collapsed":[{"name":"loop","isCollapsed":false}],"x":-3067,"y":648},{"id":"905AFE8C-0F54-49E0-837B-7132916D215C","type":"VariableBlock","disabled":false,"name":"businessGlossaryName","displayName":"Variable - businessGlossaryName","comment":"Name of the glossary containing the ISV Configuration Database","childId":"FB0667A9-B389-4ADB-9615-9555F36AA0E1","inputs":[],"settings":[],"collapsed":[{"name":"loop","isCollapsed":false}],"x":-3056,"y":456,"variableGuid":"896B2C74-4C62-4599-8B28-7328F6B3F148","operations":[{"id":"empty","key":"8D9C75E0-8AF8-4D12-A9B9-296CEAE3508D","name":"Empty { variable }","value":null},{"id":"set_value","key":"D91830D4-7C76-4DFD-B69C-1B3896DD96E1","name":"Set value of { variable }","value":"ISV Configuration Database 2"}]}],"variables":[{"guid":"4341C652-65B7-4B0A-B5B6-F1BDAB3579DB","name":"sharedSpaceName","type":"string"},{"guid":"896B2C74-4C62-4599-8B28-7328F6B3F148","name":"businessGlossaryName","type":"string"}]}